{"@context":"https://iiif.io/api/presentation/3/context.json","id":"https://canopy-iiif.github.io/canopy-iiif/api/facet/date/1939.json","type":"Collection","label":{"none":["1939"]},"items":[{"id":"https://cdm16786.contentdm.oclc.org/iiif/grandcoulee:11/manifest.json","type":"Manifest","label":{"none":["Burning brush and tree limbs, 1939."]},"thumbnail":[{"id":"https://cdm16786.contentdm.oclc.org/iiif/2/grandcoulee:11/full/410,/0/default.jpg","type":"Image","format":"image/jpeg","width":410,"height":512}],"homepage":[{"id":"https://canopy-iiif.github.io/canopy-iiif/works/burning-brush-and-tree-limbs-1939","type":"Text","label":{"none":["Burning brush and tree limbs, 1939."]}}]},{"id":"https://cdm16786.contentdm.oclc.org/iiif/grandcoulee:26/manifest.json","type":"Manifest","label":{"none":["Hams ready for the oven at Camp Keller, 1939."]},"thumbnail":[{"id":"https://cdm16786.contentdm.oclc.org/iiif/2/grandcoulee:26/full/384,/0/default.jpg","type":"Image","format":"image/jpeg","width":384,"height":309}],"homepage":[{"id":"https://canopy-iiif.github.io/canopy-iiif/works/hams-ready-for-the-oven-at-camp-keller-1939","type":"Text","label":{"none":["Hams ready for the oven at Camp Keller, 1939."]}}]},{"id":"https://cdm16786.contentdm.oclc.org/iiif/grandcoulee:39/manifest.json","type":"Manifest","label":{"none":["The Pup -- a floating tool shed, supply room and shop, 1939."]},"thumbnail":[{"id":"https://cdm16786.contentdm.oclc.org/iiif/2/grandcoulee:39/full/384,/0/default.jpg","type":"Image","format":"image/jpeg","width":384,"height":311}],"homepage":[{"id":"https://canopy-iiif.github.io/canopy-iiif/works/the-pup-a-floating-tool-shed-supply-room-and-shop-1939","type":"Text","label":{"none":["The Pup -- a floating tool shed, supply room and shop, 1939."]}}]},{"id":"https://cdm16786.contentdm.oclc.org/iiif/grandcoulee:52/manifest.json","type":"Manifest","label":{"none":["Recreation room aboard Camp Ferry, 1939"]},"thumbnail":[{"id":"https://cdm16786.contentdm.oclc.org/iiif/2/grandcoulee:52/full/384,/0/default.jpg","type":"Image","format":"image/jpeg","width":384,"height":307}],"homepage":[{"id":"https://canopy-iiif.github.io/canopy-iiif/works/recreation-room-aboard-camp-ferry-1939","type":"Text","label":{"none":["Recreation room aboard Camp Ferry, 1939"]}}]},{"id":"https://cdm16786.contentdm.oclc.org/iiif/grandcoulee:99/manifest.json","type":"Manifest","label":{"none":["Clearing activities in the reservoir area above the dam, Washington, 1939."]},"thumbnail":[{"id":"https://cdm16786.contentdm.oclc.org/iiif/2/grandcoulee:99/full/384,/0/default.jpg","type":"Image","format":"image/jpeg","width":384,"height":307}],"homepage":[{"id":"https://canopy-iiif.github.io/canopy-iiif/works/clearing-activities-in-the-reservoir-area-above-the-dam-washington-1939","type":"Text","label":{"none":["Clearing activities in the reservoir area above the dam, Washington, 1939."]}}]},{"id":"https://cdm16786.contentdm.oclc.org/iiif/grandcoulee:102/manifest.json","type":"Manifest","label":{"none":["Moving Camp Ferry, 1939"]},"thumbnail":[{"id":"https://cdm16786.contentdm.oclc.org/iiif/2/grandcoulee:102/full/384,/0/default.jpg","type":"Image","format":"image/jpeg","width":384,"height":309}],"homepage":[{"id":"https://canopy-iiif.github.io/canopy-iiif/works/moving-camp-ferry-1939","type":"Text","label":{"none":["Moving Camp Ferry, 1939"]}}]},{"id":"https://cdm16786.contentdm.oclc.org/iiif/grandcoulee:107/manifest.json","type":"Manifest","label":{"none":["Camp Ferry crew on their way to lunch, 1939."]},"thumbnail":[{"id":"https://cdm16786.contentdm.oclc.org/iiif/2/grandcoulee:107/full/384,/0/default.jpg","type":"Image","format":"image/jpeg","width":384,"height":298}],"homepage":[{"id":"https://canopy-iiif.github.io/canopy-iiif/works/camp-ferry-crew-on-their-way-to-lunch-1939","type":"Text","label":{"none":["Camp Ferry crew on their way to lunch, 1939."]}}]},{"id":"https://cdm16786.contentdm.oclc.org/iiif/grandcoulee:117/manifest.json","type":"Manifest","label":{"none":["Mr. & Mrs. Smythe of Kettle Falls, 1939."]},"thumbnail":[{"id":"https://cdm16786.contentdm.oclc.org/iiif/2/grandcoulee:117/full/384,/0/default.jpg","type":"Image","format":"image/jpeg","width":384,"height":306}],"homepage":[{"id":"https://canopy-iiif.github.io/canopy-iiif/works/mr-and-mrs-smythe-of-kettle-falls-1939","type":"Text","label":{"none":["Mr. & Mrs. Smythe of Kettle Falls, 1939."]}}]},{"id":"https://cdm16786.contentdm.oclc.org/iiif/grandcoulee:741/manifest.json","type":"Manifest","label":{"none":["Five men pulling in the last gangplank before Camp Ferry moves to a new location,  1939"]},"thumbnail":[{"id":"https://cdm16786.contentdm.oclc.org/iiif/2/grandcoulee:741/full/384,/0/default.jpg","type":"Image","format":"image/jpeg","width":384,"height":307}],"homepage":[{"id":"https://canopy-iiif.github.io/canopy-iiif/works/five-men-pulling-in-the-last-gangplank-before-camp-ferry-moves-to-a-new-location-1939","type":"Text","label":{"none":["Five men pulling in the last gangplank before Camp Ferry moves to a new location,  1939"]}}]},{"id":"https://cdm16786.contentdm.oclc.org/iiif/grandcoulee:743/manifest.json","type":"Manifest","label":{"none":["The barge PAUL BUNYAN tied up to shore of the Columbia River with an air compressor on deck and a boat alongside, 1939"]},"thumbnail":[{"id":"https://cdm16786.contentdm.oclc.org/iiif/2/grandcoulee:743/full/384,/0/default.jpg","type":"Image","format":"image/jpeg","width":384,"height":311}],"homepage":[{"id":"https://canopy-iiif.github.io/canopy-iiif/works/the-barge-paul-bunyan-tied-up-to-shore-of-the-columbia-river-with-an-air-compressor-on-deck-and-a-bo","type":"Text","label":{"none":["The barge PAUL BUNYAN tied up to shore of the Columbia River with an air compressor on deck and a boat alongside, 1939"]}}]},{"id":"https://cdm16786.contentdm.oclc.org/iiif/grandcoulee:787/manifest.json","type":"Manifest","label":{"none":["Long wooden building under construction at Camp Kettle, 1939"]},"thumbnail":[{"id":"https://cdm16786.contentdm.oclc.org/iiif/2/grandcoulee:787/full/384,/0/default.jpg","type":"Image","format":"image/jpeg","width":384,"height":186}],"homepage":[{"id":"https://canopy-iiif.github.io/canopy-iiif/works/long-wooden-building-under-construction-at-camp-kettle-1939","type":"Text","label":{"none":["Long wooden building under construction at Camp Kettle, 1939"]}}]},{"id":"https://cdm16786.contentdm.oclc.org/iiif/grandcoulee:807/manifest.json","type":"Manifest","label":{"none":["Three cooks of Camp Keller and camp superintendent Harry Fenton displaying trays of roast beef for the first meal served at newly completed Camp Keller, 1939"]},"thumbnail":[{"id":"https://cdm16786.contentdm.oclc.org/iiif/2/grandcoulee:807/full/384,/0/default.jpg","type":"Image","format":"image/jpeg","width":384,"height":309}],"homepage":[{"id":"https://canopy-iiif.github.io/canopy-iiif/works/three-cooks-of-camp-keller-and-camp-superintendent-harry-fenton-displaying-trays-of-roast-beef-for-t","type":"Text","label":{"none":["Three cooks of Camp Keller and camp superintendent Harry Fenton displaying trays of roast beef for the first meal served at newly completed Camp Keller, 1939"]}}]},{"id":"https://cdm16786.contentdm.oclc.org/iiif/grandcoulee:811/manifest.json","type":"Manifest","label":{"none":["Men working on the construction of Camp Gifford re-erecting buildings transported from Camp Keller, 1939"]},"thumbnail":[{"id":"https://cdm16786.contentdm.oclc.org/iiif/2/grandcoulee:811/full/384,/0/default.jpg","type":"Image","format":"image/jpeg","width":384,"height":307}],"homepage":[{"id":"https://canopy-iiif.github.io/canopy-iiif/works/men-working-on-the-construction-of-camp-gifford-re-erecting-buildings-transported-from-camp-keller-1","type":"Text","label":{"none":["Men working on the construction of Camp Gifford re-erecting buildings transported from Camp Keller, 1939"]}}]},{"id":"https://cdm16786.contentdm.oclc.org/iiif/grandcoulee:821/manifest.json","type":"Manifest","label":{"none":["PAUL BUNYAN barge towing Camp Ferry along the Columbia River, 1939 "]},"thumbnail":[{"id":"https://cdm16786.contentdm.oclc.org/iiif/2/grandcoulee:821/full/384,/0/default.jpg","type":"Image","format":"image/jpeg","width":384,"height":309}],"homepage":[{"id":"https://canopy-iiif.github.io/canopy-iiif/works/paul-bunyan-barge-towing-camp-ferry-along-the-columbia-river-1939","type":"Text","label":{"none":["PAUL BUNYAN barge towing Camp Ferry along the Columbia River, 1939 "]}}]},{"id":"https://cdm16786.contentdm.oclc.org/iiif/grandcoulee:858/manifest.json","type":"Manifest","label":{"none":["Camp Ferry tying up to a new location with the meat storage building and toilets on the barge PAUL BUNYAN, 1939"]},"thumbnail":[{"id":"https://cdm16786.contentdm.oclc.org/iiif/2/grandcoulee:858/full/384,/0/default.jpg","type":"Image","format":"image/jpeg","width":384,"height":294}],"homepage":[{"id":"https://canopy-iiif.github.io/canopy-iiif/works/camp-ferry-tying-up-to-a-new-location-with-the-meat-storage-building-and-toilets-on-the-barge-paul-b","type":"Text","label":{"none":["Camp Ferry tying up to a new location with the meat storage building and toilets on the barge PAUL BUNYAN, 1939"]}}]}],"partOf":[{"id":"https://canopy-iiif.github.io/canopy-iiif/api/facet/date.json","type":"Collection"}],"summary":{"none":["Date"]},"homepage":[{"id":"https://canopy-iiif.github.io/canopy-iiif/search?date=1939","type":"Text","label":{"none":["1939"]}}]}