{"@context":"https://iiif.io/api/presentation/3/context.json","id":"https://mathewjordan.github.io/canopy-grand-coulee/api/facet/date/may-11-1937.json","type":"Collection","label":{"none":["May 11, 1937"]},"items":[{"id":"https://cdm16786.contentdm.oclc.org/iiif/grandcoulee:978/manifest.json","type":"Manifest","label":{"none":["Bridges and camps, Grand Coulee Dam site, May 11, 1937"]},"thumbnail":[{"id":"https://cdm16786.contentdm.oclc.org/iiif/2/grandcoulee:978/full/384,/0/default.jpg","type":"Image","format":"image/jpeg","width":384,"height":297}],"homepage":[{"id":"https://mathewjordan.github.io/canopy-grand-coulee/works/bridges-and-camps-grand-coulee-dam-site-may-11-1937","type":"Text","label":{"none":["Bridges and camps, Grand Coulee Dam site, May 11, 1937"]}}]}],"partOf":[{"id":"https://mathewjordan.github.io/canopy-grand-coulee/api/facet/date.json","type":"Collection"}],"summary":{"none":["Date"]},"homepage":[{"id":"https://mathewjordan.github.io/canopy-grand-coulee/search?date=may-11-1937","type":"Text","label":{"none":["May 11, 1937"]}}]}